LICENSE
MANIFEST.in
README.rst
setup.py
annotations/__init__.py
annotations/admin.py
annotations/forms.py
annotations/models.py
annotations/serializers.py
annotations/tests.py
annotations/urls.py
annotations/utils.py
annotations/views.py
annotations/static/css/annotations/styles.css
annotations/static/css/annotations/styles.scss
annotations/static/js/annotations/script.js
pi_annotations.egg-info/PKG-INFO
pi_annotations.egg-info/SOURCES.txt
pi_annotations.egg-info/dependency_links.txt
pi_annotations.egg-info/requires.txt
pi_annotations.egg-info/top_level.txt