Metadata-Version: 1.1
Name: pi-annotations
Version: 0.1.0
Summary: An app to create per-paragraph comments on content (created via Blogging App)
Home-page: https://github.com/PirateLearner/annotations
Author: ['Anshul Thakur']
Author-email: ['captain@piratelearner.com']
License: GPL v2
Download-URL: https://github.com/PirateLearner/annotations/archive/v0.1.0.tar.gz
Platform: UNKNOWN
Classifier: Environment :: Web Environment
Classifier: Framework :: Django
Classifier: Intended Audience :: Developers
Classifier: License :: OSI Approved :: GNU General Public License v2 or later (GPLv2+)
Classifier: Operating System :: OS Independent
Classifier: Programming Language :: Python
Classifier: Programming Language :: Python :: 2.7
Classifier: Topic :: Internet :: WWW/HTTP
Classifier: Topic :: Internet :: WWW/HTTP :: Dynamic Content
